pharmastar/__init__.py
pharmastar/analysis.py
pharmastar/chemical.py
pharmastar/chemical_herb.py
pharmastar/chemical_protein.py
pharmastar/output.py
pharmastar-0.0.1a1.dist-info/METADATA
pharmastar-0.0.1a1.dist-info/WHEEL
pharmastar-0.0.1a1.dist-info/licenses/LICENSE
pharmastar-0.0.1a1.dist-info/RECORD
