Metadata-Version: 2.1
Name: pharmastar
Version: 0.0.1a1
Summary: 药理大师是一个具有多种功能的中药网络药理学分析工具，可进行经典的网络药理学及反向网络药理学分析。Pharmastar is a multi-functional traditional chinese medicine network pharmacology analysis tool for classical network pharmacology and reverse network pharmacology.
Project-URL: Homepage, https://github.com/MLi-lab-Bioinformatics-NJUCM/pharmastar
Project-URL: Bug Tracker, https://github.com/MLi-lab-Bioinformatics-NJUCM/pharmastar/issues
Author-email: 王皓阳 <Wesady@qq.com>
License-File: LICENSE
Classifier: Development Status :: 3 - Alpha
Classifier: Intended Audience :: Healthcare Industry
Classifier: Intended Audience :: Science/Research
Classifier: License :: OSI Approved :: MIT License
Classifier: Natural Language :: Chinese (Simplified)
Classifier: Natural Language :: English
Classifier: Operating System :: OS Independent
Classifier: Programming Language :: Python :: 3
Classifier: Topic :: Scientific/Engineering :: Bio-Informatics
Classifier: Topic :: Scientific/Engineering :: Information Analysis
Requires-Python: >=3.8
